ai_aquatica/__init__.py
ai_aquatica/ai_ml_models.py
ai_aquatica/cli.py
ai_aquatica/data_cleaning.py
ai_aquatica/data_import.py
ai_aquatica/data_loading.py
ai_aquatica/data_standardization.py
ai_aquatica/data_visualization.py
ai_aquatica/ion_balance.py
ai_aquatica/missing_data.py
ai_aquatica/ml_analysis.py
ai_aquatica/report_generation.py
ai_aquatica/statistical_analysis.py
ai_aquatica/visualization.py
ai_aquatica/templates/further_analysis_template.html
ai_aquatica/templates/interpretation_report_template.html
ai_aquatica/templates/statistical_report_template.html
ai_aquatica-1.1.0.dist-info/licenses/LICENSE
tests/__init__.py
tests/test_ai_ml_models.py
tests/test_data_cleaning.py
tests/test_data_loading.py
tests/test_data_standardization.py
tests/test_ion_balance.py
tests/test_missing_data.py
tests/test_optional_dependencies.py
tests/test_public_api.py
tests/test_report_generation.py
tests/test_statistical_analysis.py
tests/test_visualization.py
ai_aquatica-1.1.0.dist-info/METADATA
ai_aquatica-1.1.0.dist-info/WHEEL
ai_aquatica-1.1.0.dist-info/entry_points.txt
ai_aquatica-1.1.0.dist-info/top_level.txt
ai_aquatica-1.1.0.dist-info/RECORD
