Metadata-Version: 2.4
Name: AI-Aquatica
Version: 1.1.0
Summary: The project is used to analyze water quality data using AI/ML tools.
Home-page: https://github.com/TyMill/AI-Aquatica
Author: Tymoteusz Miller
Author-email: me@tymoteuszmiller.dev
Keywords: water quality,machine learning,environmental analysis,ai aquatica
Classifier: Programming Language :: Python :: 3
Classifier: Programming Language :: Python :: 3.8
Classifier: Programming Language :: Python :: 3.9
Classifier: Programming Language :: Python :: 3.10
Classifier: Programming Language :: Python :: 3.11
Classifier: Programming Language :: Python :: 3.12
Classifier: License :: OSI Approved :: MIT License
Classifier: Operating System :: OS Independent
Classifier: Intended Audience :: Science/Research
Classifier: Topic :: Scientific/Engineering :: Information Analysis
Requires-Python: >=3.8
License-File: LICENSE
Requires-Dist: pandas
Requires-Dist: numpy
Requires-Dist: scikit-learn
Requires-Dist: matplotlib
Requires-Dist: seaborn
Requires-Dist: jinja2
Requires-Dist: sqlalchemy
Requires-Dist: pymongo
Requires-Dist: requests
Requires-Dist: scipy
Requires-Dist: statsmodels
Provides-Extra: deep-learning
Requires-Dist: tensorflow; extra == "deep-learning"
Provides-Extra: interactive
Requires-Dist: plotly; extra == "interactive"
Provides-Extra: testing
Requires-Dist: pytest; extra == "testing"
Provides-Extra: all
Requires-Dist: tensorflow; extra == "all"
Requires-Dist: plotly; extra == "all"
Requires-Dist: requests; extra == "all"
Requires-Dist: scipy; extra == "all"
Requires-Dist: statsmodels; extra == "all"
Requires-Dist: pytest; extra == "all"
Dynamic: license-file
